Metadata-Version: 2.1
Name: pypdist
Version: 0.1.3
Summary: Model data using univariate distributions
Home-page: UNKNOWN
Author: David Pinto
Author-email: davidengaut@gmail.com
License: UNKNOWN
Platform: UNKNOWN
